{
  "version": "v0",
  "glyph": "e",
  "position": "medial",
  "variant": 0,
  "advance": 1.0,
  "_note": "Medial e per Loth 1866 (corrected after user feedback): the Kurrent-e is FLAT and WIDE, sitting entirely within x-height — not a tall single-loop shape. The path traces three subtle peaks: (1) the entry stroke from the previous letter rises to a low arch, (2) the e-body itself peaks with the kleine Schleife/Kreuzungsfall inside it, (3) the exit stroke leaves toward the next letter via a third low arch. One continuous stroke; the Schleife is the only true self-crossing. Aspect ratio is roughly 2:1 wide-to-tall, matching the Loth alphabet-chart depiction.",
  "entry": {
    "xy": [0.0, 0.0],
    "tangent_deg": 50,
    "coupling": "baseline"
  },
  "exit": {
    "xy": [1.0, 0.0],
    "tangent_deg": 50,
    "coupling": "baseline"
  },
  "strokes": [
    {
      "curve_type": "bspline",
      "anchors": [
        [0.0, 0.0],
        [0.12, 0.35],
        [0.22, 0.55],
        [0.32, 0.7],
        [0.28, 0.55],
        [0.2, 0.45],
        [0.24, 0.32],
        [0.4, 0.4],
        [0.55, 0.55],
        [0.7, 0.45],
        [0.85, 0.25],
        [1.0, 0.0]
      ],
      "half_widths": [0.04, 0.05, 0.05, 0.06, 0.07, 0.08, 0.07, 0.05, 0.06, 0.06, 0.05, 0.04]
    }
  ]
}
